bin/ap_test.py
bin/boss_sha1sum.py
bin/ds9_live.py
bin/epics_fetch.py
bin/getDust.py
bin/get_dust.py
bin/help.py
bin/sjd.py
bin/sloan_log.py
bin/sp_version.py
bin/wave_mid.py
bin/x_mid.py
python/apogee_data.py
python/boss_data.py
python/guider_data.py
python/log_support.py
sdss_obstools-3.4.0.data/scripts/WAVEMID
sdss_obstools-3.4.0.data/scripts/XMID
sdss_obstools-3.4.0.data/scripts/ap_test.py
sdss_obstools-3.4.0.data/scripts/aptest
sdss_obstools-3.4.0.data/scripts/az_fiducial_error.sh
sdss_obstools-3.4.0.data/scripts/boss_sha1sum.py
sdss_obstools-3.4.0.data/scripts/ds9_live.py
sdss_obstools-3.4.0.data/scripts/epics_fetch.py
sdss_obstools-3.4.0.data/scripts/getDust.py
sdss_obstools-3.4.0.data/scripts/get_dust.py
sdss_obstools-3.4.0.data/scripts/help.py
sdss_obstools-3.4.0.data/scripts/mjd
sdss_obstools-3.4.0.data/scripts/sjd.py
sdss_obstools-3.4.0.data/scripts/sloan_log.py
sdss_obstools-3.4.0.data/scripts/spHelp
sdss_obstools-3.4.0.data/scripts/spVersion
sdss_obstools-3.4.0.data/scripts/sp_version.py
sdss_obstools-3.4.0.data/scripts/wave_mid.py
sdss_obstools-3.4.0.data/scripts/x_mid.py
sdss_obstools-3.4.0.dist-info/LICENSE.md
sdss_obstools-3.4.0.dist-info/METADATA
sdss_obstools-3.4.0.dist-info/WHEEL
sdss_obstools-3.4.0.dist-info/top_level.txt
sdss_obstools-3.4.0.dist-info/RECORD
