Metadata-Version: 2.1
Name: sdss-obstools
Version: 3.4.0
Summary: A library of tools for SDSS telescope operations.
Home-page: https://wiki.sdss.org/display/APO/Observing+Scripts
Author: UNKNOWN
Author-email: UNKNOWN
License: UNKNOWN
Platform: UNKNOWN
Requires-Dist: pathlib (>=1.0.0)
Requires-Dist: matplotlib (>=3.2.1)
Requires-Dist: numpy (>=1.18.4)
Requires-Dist: astropy (>=4.0.1.post1)
Requires-Dist: pyds9 (>=1.8.1)
Requires-Dist: tqdm (>=4.46.1)
Requires-Dist: channelarchiver (>=1.0.0)
Requires-Dist: seaborn (>=0.10.1)
Requires-Dist: scipy (>=1.4.1)
Requires-Dist: pyfits (>=3.5)
Requires-Dist: setuptools (>=47.1.1)
Requires-Dist: pytest-astropy
Requires-Dist: datetime (>=4.3)
Requires-Dist: fitsio (>=1.1.3)
Requires-Dist: python (>=3.7.8)
